CHANGES.txt
README.txt
bootstrap.py
buildout.cfg
setup.py
src/zope/__init__.py
src/zope.weakset.egg-info/PKG-INFO
src/zope.weakset.egg-info/SOURCES.txt
src/zope.weakset.egg-info/dependency_links.txt
src/zope.weakset.egg-info/namespace_packages.txt
src/zope.weakset.egg-info/requires.txt
src/zope.weakset.egg-info/top_level.txt
src/zope.weakset.egg-info/zip-safe
src/zope/weakset/__init__.py
src/zope/weakset/tests.py