Metadata-Version: 1.0
Name: zope.weakset
Version: 3.6.0
Summary: ZODB weakset implementation
Home-page: http://pypi.python.org/pypi/zope.weakset
Author: Zope Corporation and Contributors
Author-email: zodb-dev@zope.org
License: ZPL 2.1
Platform: any
Classifier: Development Status :: 5 - Production/Stable
Classifier: Intended Audience :: Developers
Classifier: License :: OSI Approved :: Zope Public License
Classifier: Programming Language :: Python
Classifier: Topic :: Database
Classifier: Topic :: Software Development :: Libraries :: Python Modules
Classifier: Operating System :: Microsoft :: Windows
Classifier: Operating System :: Unix
